{
  "preferredAgents": ["rn-sjc-2-a", "rn-sjc-2-b", "rn-chi-1-a"],
  "telegram": {
    "proxyTimeout": 5000,
    "preferredRegions": [],
    "targetCountries": [],
    "maxRetries": 2,
    "SmallBox": {
      "minCoins": 50,
      "minRate": 4.0,
      "minTime": 80
    },
    "BigBox": {
      "minCoins": 500,
      "minRate": 4.0,
      "minTime": 120
    },
    "shortBoxThreshold": 30,
    "enableLiveNoBox": false
  },
  "websocket": {
    "maxConnections": 1000,
    "scanDelay": 2000,
    "batchSize": 10,
    "retryDelay": 5000,
    "maxRetries": 1,
    "blacklistDuration": 1800
  },
  "api": {
    "retryDelay": 600,
    "maxRetries": 1,
    "requestDelay": 300
  },
  "file": {
    "log": "./Logs/LOG_YYYY-MM-DD.log",
    "state": "./Data/ResumeData.json"
  },
  "google": {
    "credentialsPath": "./Data/VIPKEY.json",
    "liveLogSheetId": "1OlRVc0QqkspyjbyW40pottcQbC19LuhnyzowKYjzEv8",
    "scopes": ["https://www.googleapis.com/auth/spreadsheets"]
  },
  "scan": {
    "scanSource": "file",
    "google": {
      "sheetName": "OnLog",
      "sheetColumn": "A",
      "sheetStartRow": 2
    },
    "file": {
      "path": "./Data/list.txt"
    }
  },
  "flags": {
    "enableTelegram": true
  },
  "apiQuotaLimit": 2000
}
